{
  "ID": "f9c0e3ac-c8d7-4a95-8cde-0d4145de31a1",
  "Version": "2.3.4",
  "Name": "JFItemActionInGameBottom",
  "Content": {
    "Content": {
      "Animation": {
        "Duration": 0,
        "Speed": 1.0,
        "Timelines": [],
        "ctype": "TimelineActionData"
      },
      "AnimationList": [],
      "ObjectData": {
        "Tag": 251,
        "Children": [
          {
            "FileData": {
              "Type": "PlistSubImage",
              "Path": "IMG_CIRCLE_LINE_BG.png",
              "Plist": "ScreenGame/Guns/AtlasGuns.plist"
            },
            "Scale9OriginX": 70,
            "Scale9OriginY": 38,
            "Scale9Width": 73,
            "Scale9Height": 42,
            "AnchorPoint": {
              "ScaleX": 0.5,
              "ScaleY": 0.5
            },
            "Position": {
              "X": 1.1821,
              "Y": 1.1821
            },
            "Scale": {
              "ScaleX": 1.0,
              "ScaleY": 1.0
            },
            "CColor": {},
            "IconVisible": false,
            "PrePosition": {
              "X": 0.0,
              "Y": 0.0
            },
            "PreSize": {
              "X": 0.0,
              "Y": 0.0
            },
            "LeftMargin": -105.3179,
            "RightMargin": -107.6821,
            "TopMargin": -60.1821,
            "BottomMargin": -57.8179,
            "Tag": 267,
            "ActionTag": 412601457,
            "Size": {
              "X": 213.0,
              "Y": 118.0
            },
            "Name": "JFActionLine",
            "ctype": "ImageViewObjectData"
          },
          {
            "FontSize": 14,
            "ButtonText": "",
            "TextColor": {
              "R": 65,
              "G": 65,
              "B": 70
            },
            "DisabledFileData": {
              "Type": "PlistSubImage",
              "Path": "IMG_ACTION_BG_DISABLE.png",
              "Plist": "ScreenGame/Guns/AtlasGuns.plist"
            },
            "NormalFileData": {
              "Type": "PlistSubImage",
              "Path": "IMG_ACTION_BG_NORMAL.png",
              "Plist": "ScreenGame/Guns/AtlasGuns.plist"
            },
            "Scale9Enable": true,
            "Scale9OriginX": 15,
            "Scale9OriginY": 5,
            "Scale9Width": 63,
            "Scale9Height": 83,
            "OutlineColor": {
              "G": 0,
              "B": 0
            },
            "ShadowColor": {
              "R": 110,
              "G": 110,
              "B": 110
            },
            "ShadowOffsetX": 2.0,
            "ShadowOffsetY": -2.0,
            "TouchEnable": true,
            "AnchorPoint": {
              "ScaleX": 0.5,
              "ScaleY": 0.5
            },
            "Position": {
              "X": 0.0,
              "Y": 60.0
            },
            "Scale": {
              "ScaleX": 1.0,
              "ScaleY": 1.0
            },
            "CColor": {},
            "IconVisible": false,
            "PrePosition": {
              "X": 0.0,
              "Y": 0.0
            },
            "PreSize": {
              "X": 0.0,
              "Y": 0.0
            },
            "LeftMargin": -46.5,
            "RightMargin": -46.5,
            "TopMargin": -106.5,
            "BottomMargin": 13.5,
            "Tag": 270,
            "Children": [
              {
                "FileData": {
                  "Type": "PlistSubImage",
                  "Path": "IMG_BTN_INFO.png",
                  "Plist": "ScreenGame/Guns/AtlasGuns.plist"
                },
                "Scale9OriginX": 30,
                "Scale9OriginY": 30,
                "Scale9Width": 33,
                "Scale9Height": 33,
                "AnchorPoint": {},
                "Position": {
                  "X": -0.7384,
                  "Y": 0.5774
                },
                "Scale": {
                  "ScaleX": 1.0,
                  "ScaleY": 1.0
                },
                "CColor": {},
                "IconVisible": false,
                "PrePosition": {
                  "X": -0.0079,
                  "Y": 0.0062
                },
                "PreSize": {
                  "X": 1.0,
                  "Y": 1.0
                },
                "LeftMargin": -0.7384,
                "RightMargin": 0.7384,
                "TopMargin": -0.5774,
                "BottomMargin": 0.5774,
                "Tag": 273,
                "ActionTag": 528015025,
                "Size": {
                  "X": 93.0,
                  "Y": 93.0
                },
                "Name": "ImgUserInfo",
                "ctype": "ImageViewObjectData"
              },
              {
                "FileData": {
                  "Type": "PlistSubImage",
                  "Path": "IMG_ACTION_LINE.png",
                  "Plist": "ScreenGame/Guns/AtlasGuns.plist"
                },
                "Scale9OriginX": 30,
                "Scale9OriginY": 30,
                "Scale9Width": 33,
                "Scale9Height": 33,
                "AnchorPoint": {},
                "Position": {
                  "X": 0.0,
                  "Y": 0.0
                },
                "Scale": {
                  "ScaleX": 1.0,
                  "ScaleY": 1.0
                },
                "CColor": {},
                "IconVisible": false,
                "PrePosition": {
                  "X": 0.0,
                  "Y": 0.0
                },
                "PreSize": {
                  "X": 1.0,
                  "Y": 1.0
                },
                "Tag": 1252,
                "ActionTag": -883143495,
                "Size": {
                  "X": 93.0,
                  "Y": 93.0
                },
                "Name": "ImgBackground",
                "ctype": "ImageViewObjectData"
              }
            ],
            "ActionTag": 274663441,
            "Size": {
              "X": 93.0,
              "Y": 93.0
            },
            "Name": "JFBtnUserInfo",
            "ctype": "ButtonObjectData"
          },
          {
            "FontSize": 14,
            "ButtonText": "",
            "TextColor": {
              "R": 65,
              "G": 65,
              "B": 70
            },
            "NormalFileData": {
              "Type": "PlistSubImage",
              "Path": "IMG_ACTION_LINE.png",
              "Plist": "ScreenGame/Guns/AtlasGuns.plist"
            },
            "Scale9Enable": true,
            "Scale9OriginX": 15,
            "Scale9OriginY": 5,
            "Scale9Width": 63,
            "Scale9Height": 83,
            "OutlineColor": {
              "G": 0,
              "B": 0
            },
            "ShadowColor": {
              "R": 110,
              "G": 110,
              "B": 110
            },
            "ShadowOffsetX": 2.0,
            "ShadowOffsetY": -2.0,
            "TouchEnable": true,
            "AnchorPoint": {
              "ScaleX": 0.5,
              "ScaleY": 0.5
            },
            "Position": {
              "X": -105.0,
              "Y": 10.0
            },
            "Scale": {
              "ScaleX": 1.0,
              "ScaleY": 1.0
            },
            "CColor": {},
            "IconVisible": false,
            "PrePosition": {
              "X": 0.0,
              "Y": 0.0
            },
            "PreSize": {
              "X": 0.0,
              "Y": 0.0
            },
            "LeftMargin": -151.5,
            "RightMargin": 58.5,
            "TopMargin": -56.5,
            "BottomMargin": -36.5,
            "Tag": 274,
            "Children": [
              {
                "FileData": {
                  "Type": "PlistSubImage",
                  "Path": "IMG_ACTION_BG_NORMAL.png",
                  "Plist": "ScreenGame/Guns/AtlasGuns.plist"
                },
                "Scale9OriginX": 30,
                "Scale9OriginY": 30,
                "Scale9Width": 33,
                "Scale9Height": 33,
                "AnchorPoint": {},
                "Position": {
                  "X": 0.0002,
                  "Y": 0.0
                },
                "Scale": {
                  "ScaleX": 1.0,
                  "ScaleY": 1.0
                },
                "CColor": {},
                "IconVisible": false,
                "PrePosition": {
                  "X": 0.0,
                  "Y": 0.0
                },
                "PreSize": {
                  "X": 1.0,
                  "Y": 1.0
                },
                "LeftMargin": 0.0002,
                "RightMargin": -0.0002,
                "Tag": 1249,
                "ActionTag": -830843097,
                "Size": {
                  "X": 93.0,
                  "Y": 93.0
                },
                "Name": "ImgBackgroundNormal",
                "ctype": "ImageViewObjectData"
              },
              {
                "FileData": {
                  "Type": "PlistSubImage",
                  "Path": "IMG_ACTION_BG_DISABLE.png",
                  "Plist": "ScreenGame/Guns/AtlasGuns.plist"
                },
                "Scale9OriginX": 30,
                "Scale9OriginY": 30,
                "Scale9Width": 33,
                "Scale9Height": 33,
                "AnchorPoint": {},
                "Position": {
                  "X": 0.5662,
                  "Y": -0.4015
                },
                "Scale": {
                  "ScaleX": 1.0,
                  "ScaleY": 1.0
                },
                "CColor": {},
                "IconVisible": false,
                "PrePosition": {
                  "X": 0.0061,
                  "Y": -0.0043
                },
                "PreSize": {
                  "X": 1.0,
                  "Y": 1.0
                },
                "LeftMargin": 0.5662,
                "RightMargin": -0.5662,
                "TopMargin": 0.4015,
                "BottomMargin": -0.4015,
                "Tag": 615,
                "ActionTag": -146621896,
                "Size": {
                  "X": 93.0,
                  "Y": 93.0
                },
                "VisibleForFrame": false,
                "Name": "ImgBackgroundDisable",
                "ctype": "ImageViewObjectData"
              },
              {
                "FileData": {
                  "Type": "PlistSubImage",
                  "Path": "IMG_BTN_ADD_FRIEND.png",
                  "Plist": "ScreenGame/Guns/AtlasGuns.plist"
                },
                "Scale9OriginX": 15,
                "Scale9OriginY": 15,
                "Scale9Width": 63,
                "Scale9Height": 63,
                "AnchorPoint": {},
                "Position": {
                  "X": 0.7806,
                  "Y": 0.5993
                },
                "Scale": {
                  "ScaleX": 1.0,
                  "ScaleY": 1.0
                },
                "CColor": {},
                "IconVisible": false,
                "PrePosition": {
                  "X": 0.0084,
                  "Y": 0.0064
                },
                "PreSize": {
                  "X": 1.0,
                  "Y": 1.0
                },
                "LeftMargin": 0.7806,
                "RightMargin": -0.7806,
                "TopMargin": -0.5993,
                "BottomMargin": 0.5993,
                "Tag": 277,
                "ActionTag": -1275729697,
                "Size": {
                  "X": 93.0,
                  "Y": 93.0
                },
                "Name": "ImgAddFriend",
                "ctype": "ImageViewObjectData"
              }
            ],
            "ActionTag": 711684278,
            "Size": {
              "X": 93.0,
              "Y": 93.0
            },
            "Name": "JFBtnAddFriend",
            "ctype": "ButtonObjectData"
          },
          {
            "FontSize": 14,
            "ButtonText": "",
            "TextColor": {
              "R": 65,
              "G": 65,
              "B": 70
            },
            "NormalFileData": {
              "Type": "PlistSubImage",
              "Path": "IMG_ACTION_LINE.png",
              "Plist": "ScreenGame/Guns/AtlasGuns.plist"
            },
            "Scale9Enable": true,
            "Scale9OriginX": 15,
            "Scale9OriginY": 5,
            "Scale9Width": 63,
            "Scale9Height": 83,
            "OutlineColor": {
              "G": 0,
              "B": 0
            },
            "ShadowColor": {
              "R": 110,
              "G": 110,
              "B": 110
            },
            "ShadowOffsetX": 2.0,
            "ShadowOffsetY": -2.0,
            "TouchEnable": true,
            "AnchorPoint": {
              "ScaleX": 0.5,
              "ScaleY": 0.5
            },
            "Position": {
              "X": 105.0,
              "Y": 10.0
            },
            "Scale": {
              "ScaleX": 1.0,
              "ScaleY": 1.0
            },
            "CColor": {},
            "IconVisible": false,
            "PrePosition": {
              "X": 0.0,
              "Y": 0.0
            },
            "PreSize": {
              "X": 0.0,
              "Y": 0.0
            },
            "LeftMargin": 58.5,
            "RightMargin": -151.5,
            "TopMargin": -56.5,
            "BottomMargin": -36.5,
            "Tag": 278,
            "Children": [
              {
                "FileData": {
                  "Type": "PlistSubImage",
                  "Path": "IMG_ACTION_BG_NORMAL.png",
                  "Plist": "ScreenGame/Guns/AtlasGuns.plist"
                },
                "Scale9OriginX": 30,
                "Scale9OriginY": 30,
                "Scale9Width": 33,
                "Scale9Height": 33,
                "AnchorPoint": {},
                "Position": {
                  "X": 0.0,
                  "Y": 0.0
                },
                "Scale": {
                  "ScaleX": 1.0,
                  "ScaleY": 1.0
                },
                "CColor": {},
                "IconVisible": false,
                "PrePosition": {
                  "X": 0.0,
                  "Y": 0.0
                },
                "PreSize": {
                  "X": 1.0,
                  "Y": 1.0
                },
                "Tag": 64,
                "ActionTag": -894854738,
                "Size": {
                  "X": 93.0,
                  "Y": 93.0
                },
                "Name": "ImgBackgroundNormal",
                "ctype": "ImageViewObjectData"
              },
              {
                "FileData": {
                  "Type": "PlistSubImage",
                  "Path": "IMG_ACTION_BG_DISABLE.png",
                  "Plist": "ScreenGame/Guns/AtlasGuns.plist"
                },
                "Scale9OriginX": 30,
                "Scale9OriginY": 30,
                "Scale9Width": 33,
                "Scale9Height": 33,
                "AnchorPoint": {},
                "Position": {
                  "X": 0.7093,
                  "Y": -0.0237
                },
                "Scale": {
                  "ScaleX": 1.0,
                  "ScaleY": 1.0
                },
                "CColor": {},
                "IconVisible": false,
                "PrePosition": {
                  "X": 0.0076,
                  "Y": -0.0003
                },
                "PreSize": {
                  "X": 1.0,
                  "Y": 1.0
                },
                "LeftMargin": 0.7093,
                "RightMargin": -0.7093,
                "TopMargin": 0.0237,
                "BottomMargin": -0.0237,
                "Tag": 65,
                "ActionTag": 921947233,
                "Size": {
                  "X": 93.0,
                  "Y": 93.0
                },
                "VisibleForFrame": false,
                "Name": "ImgBackgroundDisable",
                "ctype": "ImageViewObjectData"
              },
              {
                "FileData": {
                  "Type": "PlistSubImage",
                  "Path": "IMG_BTN_CHAT.png",
                  "Plist": "ScreenGame/Guns/AtlasGuns.plist"
                },
                "Scale9OriginX": 15,
                "Scale9OriginY": 15,
                "Scale9Width": 63,
                "Scale9Height": 63,
                "AnchorPoint": {},
                "Position": {
                  "X": -0.3827,
                  "Y": 1.0183
                },
                "Scale": {
                  "ScaleX": 1.0,
                  "ScaleY": 1.0
                },
                "CColor": {},
                "IconVisible": false,
                "PrePosition": {
                  "X": -0.0041,
                  "Y": 0.0109
                },
                "PreSize": {
                  "X": 1.0,
                  "Y": 1.0
                },
                "LeftMargin": -0.3827,
                "RightMargin": 0.3827,
                "TopMargin": -1.0183,
                "BottomMargin": 1.0183,
                "Tag": 281,
                "ActionTag": -493274748,
                "Size": {
                  "X": 93.0,
                  "Y": 93.0
                },
                "Name": "ImgChat",
                "ctype": "ImageViewObjectData"
              }
            ],
            "ActionTag": 483625805,
            "Size": {
              "X": 93.0,
              "Y": 93.0
            },
            "Name": "JFBtnChat",
            "ctype": "ButtonObjectData"
          }
        ],
        "Size": {
          "X": 0.0,
          "Y": 0.0
        },
        "Name": "JFItemAction",
        "ctype": "SingleNodeObjectData"
      },
      "UsedResources": [
        "ScreenGame/Guns/AtlasGuns.plist",
        "ScreenGame/Guns/AtlasGuns.png"
      ],
      "ctype": "GameFileData"
    }
  },
  "Type": "Node"
}